{
  "$schema": "https://developer.microsoft.com/json-schemas/spfx-build/package-solution.schema.json",
  "solution": {
    "name": "planner-tasks-client-side-solution",
    "id": "affe7b3e-fbfc-48bb-94b7-91f671e7ea49",
    "version": "1.4.0.0",
    "includeClientSideAssets": true,
    "skipFeatureDeployment": true,
    "isDomainIsolated": false,
    "developer": {
      "name": "",
      "websiteUrl": "",
      "privacyUrl": "",
      "termsOfUseUrl": "",
      "mpnId": "Undefined-1.17.2"
    },
    "metadata": {
      "shortDescription": {
        "default": "planner-tasks description"
      },
      "longDescription": {
        "default": "planner-tasks description"
      },
      "screenshotPaths": [],
      "videoUrl": "",
      "categories": []
    },
    "features": [
      {
        "title": "planner-tasks Feature",
        "description": "The feature that activates elements of the planner-tasks solution.",
        "id": "4a8fdd6e-ba45-4ff2-9152-e7b703442d35",
        "version": "1.0.0.0"
      }
    ],
    "webApiPermissionRequests": [
      {
        "resource": "Microsoft Graph",
        "scope": "Tasks.Read"
      },
      {
        "resource": "Microsoft Graph",
        "scope": "Tasks.ReadWrite"
      },
      {
        "resource": "Microsoft Graph",
        "scope": "Group.Read.All"
      },      
      {
        "resource": "Microsoft Graph",
        "scope": "Group.ReadWrite.All"
      }
    ]
  },
  "paths": {
    "zippedPackage": "solution/planner-tasks.sppkg"
  }
}
